prismlens/__init__.py
prismlens/prismlens.py
prismlens-0.3.6.dist-info/METADATA
prismlens-0.3.6.dist-info/WHEEL
prismlens-0.3.6.dist-info/entry_points.txt
prismlens-0.3.6.dist-info/RECORD
